asn1tool
