Metadata-Version: 2.1
Name: asn1tool
Version: 0.167.1
Summary: ASN.1 parsing, encoding and decoding.
Author: Erik Moqvist
License: MIT
Keywords: ASN.1,asn1
Classifier: License :: OSI Approved :: MIT License
Classifier: Programming Language :: Python :: 2
Classifier: Programming Language :: Python :: 3
License-File: LICENSE
Requires-Dist: pyparsing
Requires-Dist: typing_extensions
Provides-Extra: shell
Requires-Dist: prompt_toolkit; extra == "shell"
Provides-Extra: cache
Requires-Dist: diskcache; extra == "cache"
